nettoolkit_db/__init__.py
nettoolkit_db/convertdict.py
nettoolkit_db/database.py
nettoolkit_db-0.0.2.dist-info/LICENSE
nettoolkit_db-0.0.2.dist-info/METADATA
nettoolkit_db-0.0.2.dist-info/WHEEL
nettoolkit_db-0.0.2.dist-info/top_level.txt
nettoolkit_db-0.0.2.dist-info/RECORD
